semanticsearch/__init__.py
semanticsearch/config.py
semanticsearch/pretrained.py
semanticsearch/search.py
semanticsearch/utils.py
semantic_search_faiss-0.1.0.dist-info/LICENSE
semantic_search_faiss-0.1.0.dist-info/METADATA
semantic_search_faiss-0.1.0.dist-info/WHEEL
semantic_search_faiss-0.1.0.dist-info/top_level.txt
semantic_search_faiss-0.1.0.dist-info/RECORD
