Metadata-Version: 2.1
Name: semantic-search-faiss
Version: 0.1.0
Summary: Semantic search to query covid related papers
Home-page: https://github.com/Nandhagopalan/Semanticsearch
Author: Nandhagopalan Elangovan
License: MIT
Keywords: natural language processing,semantic search,pytorch
Platform: UNKNOWN
Classifier: License :: OSI Approved :: MIT License
Classifier: Intended Audience :: Developers
Classifier: Intended Audience :: Science/Research
Classifier: Operating System :: OS Independent
Classifier: Programming Language :: Python
Classifier: Programming Language :: Python :: 3
Classifier: Topic :: Software Development :: Libraries
Classifier: Topic :: Software Development :: Libraries :: Python Modules
License-File: LICENSE
Requires-Dist: certifi (==2021.5.30)
Requires-Dist: chardet (==4.0.0)
Requires-Dist: click (==8.0.1)
Requires-Dist: dataclasses
Requires-Dist: faiss-cpu (==1.7.1)
Requires-Dist: filelock (==3.0.12)
Requires-Dist: huggingface-hub (==0.0.8)
Requires-Dist: idna (==2.10)
Requires-Dist: importlib-metadata (==4.5.0)
Requires-Dist: joblib (==1.0.1)
Requires-Dist: nltk (==3.6.2)
Requires-Dist: numpy (==1.19.5)
Requires-Dist: packaging (==20.9)
Requires-Dist: pandas (==1.1.5)
Requires-Dist: Pillow (==8.2.0)
Requires-Dist: pyparsing (==2.4.7)
Requires-Dist: python-dateutil (==2.8.1)
Requires-Dist: pytz (==2021.1)
Requires-Dist: regex (==2021.4.4)
Requires-Dist: requests (==2.25.1)
Requires-Dist: sacremoses (==0.0.45)
Requires-Dist: scikit-learn (==0.24.2)
Requires-Dist: scipy (==1.5.4)
Requires-Dist: sentence-transformers (==1.2.0)
Requires-Dist: sentencepiece (==0.1.95)
Requires-Dist: six (==1.16.0)
Requires-Dist: threadpoolctl (==2.1.0)
Requires-Dist: tokenizers (==0.10.3)
Requires-Dist: torch (==1.8.1)
Requires-Dist: torchvision (==0.9.1)
Requires-Dist: tqdm (==4.61.0)
Requires-Dist: transformers (==4.6.1)
Requires-Dist: typing-extensions (==3.10.0.0)
Requires-Dist: urllib3 (==1.26.5)
Requires-Dist: zipp (==3.4.1)
